GCoCF/__init__.py
GCoCF/__main__.py
GCoCF/api.py
GCoCF/formatters.py
GCoCF/models.py
GCoCF/notifiers.py
GCoCF/utils.py
GCoCF/locales/messages.pot
gcocf-0.10.3.dist-info/entry_points.txt
gcocf-0.10.3.dist-info/LICENSE.txt
gcocf-0.10.3.dist-info/WHEEL
gcocf-0.10.3.dist-info/METADATA
gcocf-0.10.3.dist-info/RECORD
